LieshouTixi/README.md
LieshouTixi/__init__.py
LieshouTixi/__main__.py
LieshouTixi/file.epub
LieshouTixi/index.html
LieshouTixi/css/__init__.py
LieshouTixi/css/annotations.css
LieshouTixi/css/main.css
LieshouTixi/css/normalize.css
LieshouTixi/css/popup.css
LieshouTixi/font/__init__.py
LieshouTixi/font/fontello.eot
LieshouTixi/font/fontello.svg
LieshouTixi/font/fontello.ttf
LieshouTixi/font/fontello.woff
LieshouTixi/img/__init__.py
LieshouTixi/img/annotator-glyph-sprite.png
LieshouTixi/img/annotator-icon-sprite.png
LieshouTixi/img/apple-touch-icon.png
LieshouTixi/img/cancelfullscreen.png
LieshouTixi/img/close.png
LieshouTixi/img/fullscreen.png
LieshouTixi/img/loader.gif
LieshouTixi/img/menu-icon.png
LieshouTixi/img/save.png
LieshouTixi/img/saved.png
LieshouTixi/img/settings-s.png
LieshouTixi/img/settings.png
LieshouTixi/img/star.png
LieshouTixi/js/__init__.py
LieshouTixi/js/epub.js
LieshouTixi/js/epub.min.js
LieshouTixi/js/epub.min.map
LieshouTixi/js/hooks.min.js
LieshouTixi/js/hooks.min.map
LieshouTixi/js/reader.js
LieshouTixi/js/reader.js.map
LieshouTixi/js/reader.min.js
LieshouTixi/js/reader.min.map
LieshouTixi/js/hooks/__init__.py
LieshouTixi/js/hooks/extensions/__init__.py
LieshouTixi/js/hooks/extensions/highlight.js
LieshouTixi/js/libs/__init__.py
LieshouTixi/js/libs/jquery.min.js
LieshouTixi/js/libs/localforage.min.js
LieshouTixi/js/libs/screenfull.js
LieshouTixi/js/libs/screenfull.min.js
LieshouTixi/js/libs/zip.min.js
LieshouTixi/js/plugins/__init__.py
LieshouTixi/js/plugins/hypothesis.js
LieshouTixi/js/plugins/search.js
lieshou_tixi-2022.10.11.0.dist-info/METADATA
lieshou_tixi-2022.10.11.0.dist-info/WHEEL
lieshou_tixi-2022.10.11.0.dist-info/entry_points.txt
lieshou_tixi-2022.10.11.0.dist-info/top_level.txt
lieshou_tixi-2022.10.11.0.dist-info/RECORD
